cupyram/__init__.py
cupyram/_version.py
cupyram/batching.py
cupyram/benchmark.py
cupyram/cupyram.py
cupyram/fused_kernel.py
cupyram/matrc.py
cupyram/outpt.py
cupyram/pade.py
cupyram/profl.py
cupyram/solve.py
cupyram/updat.py
cupyram-0.3.0.dist-info/METADATA
cupyram-0.3.0.dist-info/WHEEL
cupyram-0.3.0.dist-info/entry_points.txt
cupyram-0.3.0.dist-info/licenses/LICENSE
cupyram-0.3.0.dist-info/RECORD
