Metadata-Version: 2.4
Name: cupyram
Version: 0.3.0
Summary: GPU-accelerated Range-dependent Acoustic Model (RAM) using CuPy
Project-URL: Homepage, https://github.com/clapeyre/cupyram
Project-URL: Repository, https://github.com/clapeyre/cupyram
Project-URL: Issues, https://github.com/clapeyre/cupyram/issues
Author-email: "Dr. Corentin J. Lapeyre" <corentin.lapeyre@gmail.com>
License: BSD-3-Clause
License-File: LICENSE
Keywords: acoustics,cuda,gpu,parabolic-equation,ram,underwater
Classifier: Development Status :: 4 - Beta
Classifier: Environment :: GPU :: NVIDIA CUDA
Classifier: Intended Audience :: Science/Research
Classifier: License :: OSI Approved :: BSD License
Classifier: Programming Language :: Python :: 3
Classifier: Programming Language :: Python :: 3.9
Classifier: Programming Language :: Python :: 3.10
Classifier: Programming Language :: Python :: 3.11
Classifier: Programming Language :: Python :: 3.12
Classifier: Topic :: Scientific/Engineering :: Physics
Requires-Python: >=3.9
Requires-Dist: click>=8.0.0
Requires-Dist: numba-cuda>=0.23.0
Requires-Dist: numba>=0.59.0
Requires-Dist: numpy>=1.20.0
Requires-Dist: nvtx>=0.2.14
Requires-Dist: tqdm>=4.67.1
Provides-Extra: cuda11
Requires-Dist: cupy-cuda11x>=13.0.0; extra == 'cuda11'
Provides-Extra: cuda12
Requires-Dist: cupy-cuda12x>=13.0.0; extra == 'cuda12'
Provides-Extra: cuda13
Requires-Dist: cupy-cuda13x>=13.0.0; extra == 'cuda13'
Provides-Extra: test
Requires-Dist: matplotlib; extra == 'test'
Requires-Dist: pyram; extra == 'test'
Requires-Dist: pytest-cov>=3.0.0; extra == 'test'
Requires-Dist: pytest>=7.0.0; extra == 'test'
Requires-Dist: scipy; extra == 'test'
